remotevbox/__init__.py
remotevbox/api.py
remotevbox/machine.py
remotevbox/vbox.py
remotevbox/websession_manager.py
remotevbox-0.1.dist-info/DESCRIPTION.rst
remotevbox-0.1.dist-info/METADATA
remotevbox-0.1.dist-info/RECORD
remotevbox-0.1.dist-info/WHEEL
remotevbox-0.1.dist-info/metadata.json
remotevbox-0.1.dist-info/top_level.txt
