Metadata-Version: 2.0
Name: remotevbox
Version: 0.1
Summary: Simple client library to work with VirtualBox remotely
Home-page: https://github.com/ilyaglow/remote-virtualbox
Author: Ilya Glotov
Author-email: ilya@ilyaglotov.com
License: LICENSE
Keywords: virtualbox soap remote
Platform: UNKNOWN
Requires-Python: >=2.7
Requires-Dist: zeep (>=2.4.0)
